__init__.py
database/engine.py
database/schema/base.py
database/schema/client/client.py
database/schema/client/contact.py
database/schema/client/note.py
database/schema/collection/collection.py
database/schema/collection/foursquare/place.py
database/schema/collection/google/places/detail.py
database/schema/collection/google/places/search.py
database/schema/collection/google/search/search.py
database/schema/collection/webscrape/webscrape.py
database/schema/project/epoch.py
database/schema/project/notes.py
database/schema/project/project.py
database/utils/fields/custom_uuid.py
database/utils/methods/repr.py
datasoup-0.0.1.dist-info/LICENCE
datasoup-0.0.1.dist-info/METADATA
datasoup-0.0.1.dist-info/WHEEL
datasoup-0.0.1.dist-info/top_level.txt
datasoup-0.0.1.dist-info/RECORD
