Metadata-Version: 2.1
Name: datasoup
Version: 0.0.1
Summary: A Python package to manage data storage, hosting, collection and processing.
Author-email: Guy de Winton <guy@codehippie.io>
Project-URL: Homepage, https://gitlab.com/guydewinton/datasoup
Project-URL: Bug Tracker, https://gitlab.com/guydewinton/datasoup/issues
Classifier: Programming Language :: Python :: 3
Classifier: License :: OSI Approved :: MIT License
Classifier: Operating System :: OS Independent
Requires-Python: >=3.7
License-File: LICENCE
Requires-Dist: sqlalchemy (>=2.0)
